README.rst
setup.py
sbackup2/__init__.py
sbackup2/cli.py
sbackup2/conf.py
sbackup2/hash.py
sbackup2/log.py
sbackup2/task.py
sbackup2/utils.py
sbackup2/version.py
sbackup2.egg-info/PKG-INFO
sbackup2.egg-info/SOURCES.txt
sbackup2.egg-info/dependency_links.txt
sbackup2.egg-info/entry_points.txt
sbackup2.egg-info/requires.txt
sbackup2.egg-info/top_level.txt